lazy_model/__init__.py
lazy_model/main.py
lazy_model-0.0.4.dist-info/WHEEL
lazy_model-0.0.4.dist-info/METADATA
lazy_model-0.0.4.dist-info/RECORD
